iflb/__init__.py
iflb/collections.py
iflb-0.0.1.dist-info/METADATA
iflb-0.0.1.dist-info/WHEEL
iflb-0.0.1.dist-info/top_level.txt
iflb-0.0.1.dist-info/RECORD
