Metadata-Version: 2.1
Name: iflb
Version: 0.0.1
Summary: Inelligent Framework Libraries
Home-page: https://github.com/iflb/iflb
Author: teppei@iflab.tokyo
Author-email: teppei@iflab.tokyo
License: UNKNOWN
Project-URL: Project Owner, http://www.pcl.cs.waseda.ac.jp/
Keywords: configuration argparse configparser logging
Platform: UNKNOWN
Classifier: Development Status :: 2 - Pre-Alpha
Classifier: Intended Audience :: Developers
Classifier: Topic :: Software Development :: Build Tools
Classifier: License :: OSI Approved :: MIT License
Classifier: Programming Language :: Python :: 3
Classifier: Operating System :: OS Independent
Requires-Python: >=3.5
